mydemocalculator/__init__.py
mydemocalculator/operation.py
mydemocalculator-0.1.0.dist-info/METADATA
mydemocalculator-0.1.0.dist-info/WHEEL
mydemocalculator-0.1.0.dist-info/entry_points.txt
mydemocalculator-0.1.0.dist-info/RECORD
